django_persiandate_widget-1.0b2.dist-info/DESCRIPTION.rst
django_persiandate_widget-1.0b2.dist-info/METADATA
django_persiandate_widget-1.0b2.dist-info/metadata.json
django_persiandate_widget-1.0b2.dist-info/pbr.json
django_persiandate_widget-1.0b2.dist-info/RECORD
django_persiandate_widget-1.0b2.dist-info/top_level.txt
django_persiandate_widget-1.0b2.dist-info/WHEEL
persiandate/jalali.py
persiandate/widgets.py
persiandate/__init__.py
persiandate/static/css/persian-datepicker-0.4.5.css
persiandate/static/js/persian-date.js
persiandate/static/js/persian-datepicker-0.4.5.js
persiandate/static/js/persian-datepicker-0.4.5.min.js
persiandate/static/js/persianDateLoad.js
