Metadata-Version: 2.0
Name: django-persiandate-widget
Version: 1.0b2
Summary: ویدجتی برای نمایش تاریخ به فرمت جلالی به همراه یک تقویم برای ورود آسان داده
Home-page: http://www.example.com/
Author: Your Name
Author-email: lkn2993@gmail.com
License: BSD 3-Clause License
Keywords: widgets persian
Platform: UNKNOWN
Classifier: Development Status :: 4 - Beta
Classifier: Environment :: Web Environment
Classifier: Framework :: Django
Classifier: Intended Audience :: Developers
Classifier: License :: OSI Approved :: BSD License
Classifier: Operating System :: OS Independent
Classifier: Programming Language :: Python
Classifier: Programming Language :: Python :: 3
Classifier: Programming Language :: Python :: 3.2
Classifier: Programming Language :: Python :: 3.3
Classifier: Programming Language :: Python :: 3.4
Classifier: Topic :: Internet :: WWW/HTTP
Classifier: Topic :: Utilities
Requires-Dist: django
